AUTHORS.txt
CHANGES.rst
CLASSIFIERS.txt
LICENSE
MANIFEST.in
README.rst
REQUIREMENTS.txt
setup.py
flaskserver/__init__.py
flaskserver/__init__.pyc
flaskserver/flask.conf
flaskserver/main.py
flaskserver.egg-info/PKG-INFO
flaskserver.egg-info/SOURCES.txt
flaskserver.egg-info/dependency_links.txt
flaskserver.egg-info/entry_points.txt
flaskserver.egg-info/requires.txt
flaskserver.egg-info/top_level.txt
flaskserver/__pycache__/__init__.cpython-34.pyc
flaskserver/templates/back.gif
flaskserver/templates/dirs.html
flaskserver/templates/file.gif
flaskserver/templates/folder.gif